Workbook

Sheet Startup Expenses
A1: STARTUP EXPENSES | D1: MyHydrationPack
B2: A NOTE BEFORE USING THIS WORKSHEET Nearly everyone who has ever started a business has underestimated costs and then faced the danger of running with inadequate capital reserves. The key to avoiding this pitfall is to adopt a rigorous approach to your research and planning. Our Startup Expenses template will guide you through the process. BEGIN BY ESTIMATING EXPENSES What will it cost you to get your business up and running? The key to accuracy here is attention to detail. For each category of expense, draw up a list of everything you will need to purchase. This will include both tangible assets (for example, equipment, inventory) and services (for example, remodeling, insurance). Then determine where you might purchase these goods or services. Research more than one vendor; i.e.: comparison shop. Do not look at price alone; terms of payment, delivery, reliability, and service are also important.
B4: STARTUP EXPENSES (annual)
B5: Website, Software, Utilities, Rent | D5: AMOUNT
B6: Shopify | D6: 587.88
B7: Adobe Creative Cloud | D7: 959.88
B8: URL: MyHydrationPack.com | D8: 15.17
B9: Microsoft 365 1 TB One Drive | D9: 74.19
B10: Phone Service | D10: 1029.48
B11: Internet Service | D11: 755.88
B12: Rent | D12: 10320
B13: Total | D13: =SUBTOTAL(109,RealEstate[AMOUNT]) -> 13742.48
B15: Licenses | D15: AMOUNT
B16: Michigan LLC | D16: 35
B17: DBA | D17: 25
B18: Sales License
B19: Vending License | D19: 0
B20: Trademark MyHydrationPack | D20: 0
B21: Product Insurance
B22: Fiber Optic Patent
B23: Total | D23: =SUBTOTAL(109,Improvements[AMOUNT]) -> 60
B25: CAPITAL EQUIPMENT LIST | D25: AMOUNT
B26: Laptop | D26: 0
B27: 2016 Volvos s60 | D27: 0
B28: Fixtures | D28: 0
B29: Machinery | D29: 0
B30: Other | D30: 0
B31: Total | D31: =SUBTOTAL(109,Capital[AMOUNT]) -> 0
B33: LOCATION AND ADMIN EXPENSES | D33: AMOUNT
B34: Rental | D34: 0
B35: Utility deposits | D35: 0
B36: Legal and accounting fees | D36: 0
B37: Prepaid insurance | D37: 0
B38: Pre-opening salaries | D38: 0
B39: Other | D39: 0
B40: Total | D40: =SUBTOTAL(109,AdminExpenses[AMOUNT]) -> 0
B42: OPENING INVENTORY | D42: AMOUNT
B43: Baby Steps Hydration Packs | D43: 0
B44: MHP Fiber Optics Hydration pack | D44: 0
B45: Replacement Bladder | D45: 0
B46: Category 4 | D46: 0
B47: Category 5 | D47: 0
B48: Total | D48: =SUBTOTAL(109,OpeningInventory[AMOUNT]) -> 0
B50: ADVERTISING AND PROMOTIONAL EXPENSES | D50: AMOUNT
B51: Advertising | D51: 0
B52: Signage | D52: 0
B53: Printing | D53: 0
B54: Travel/entertainment | D54: 0
B55: Other/additional categories | D55: 0
B56: Total | D56: =SUBTOTAL(109,PromoExpenses[AMOUNT]) -> 0
B58: OTHER EXPENSES | D58: AMOUNT
B59: Other expense 1 | D59: 0
B60: Other expense 2 | D60: 0
B61: Total | D61: =SUBTOTAL(109,OtherExpenses[AMOUNT]) -> 0
B63: Reserve for Contingencies | D63: 0
B65: Working Capital | D65: 0
B67: ADD A RESERVE FOR CONTINGENCIES Be sure to explain in your narrative how you decided on the amount you are putting into this reserve. DETERMINE YOUR CASH FLOW You cannot open with an empty bank account. You need a cash cushion to meet expenses while the business gets going. Eventually you should do a 12-month cash flow projection. This is where you will work out your estimate of working capital needs. For now, either leave this line blank or put in your best rough guess. After you have completed your cash flow, you can come back and enter the carefully researched amount. ENTER YOUR SOURCES OF CAPITAL Now that you have estimated how much capital will be needed to start, you should turn your attention to the top part of this worksheet. Enter the amounts you will put in yourself, how much will be injected by partners or investors, and how much will be supplied by borrowing.
B69: SOURCES OF CAPITAL
B70: OWNERS' INVESTMENT (NAME & OWNERSHIP %) | D70: AMOUNT
B71: Thomas Nalian and 100% | D71: 0
B72: Other investor | D72: 0
B73: Other investor | D73: 0
B74: Other investor | D74: 0
B75: Total | D75: =SUBTOTAL(109,OwnersInvestments[AMOUNT]) -> 0
B77: BANK LOANS | D77: AMOUNT
B78: Bank 1 | D78: 0
B79: Bank 2 | D79: 0
B80: Bank 3 | D80: 0
B81: Bank 4 | D81: 0
B82: Total | D82: =SUBTOTAL(109,BankLoans[AMOUNT]) -> 0
B84: OTHER LOANS | D84: AMOUNT
B85: Source 1 | D85: 0
B86: Source 2 | D86: 0
B87: Total | D87: =SUBTOTAL(109,OtherLoans[AMOUNT]) -> 0
B89: PROVIDE PROOF OF COLLATERAL If you will be using this plan to support a bank loan request, use the section near the bottom to show what assets are offered as collateral to secure the loan and estimate of the value of these items. Be prepared to offer some proof of your estimates of collateral values.
B91: SUMMARY STATEMENT
B92: SOURCE OF CAPITAL | D92: TOTALS
B93: Owners' and other investments | D93: =OwnersInvestments[[#Totals],[AMOUNT]] -> 0
B94: Bank loans | D94: =BankLoans[[#Totals],[AMOUNT]] -> 0
B95: Other loans | D95: =OtherLoans[[#Totals],[AMOUNT]] -> 0
B96: Total | D96: =SUBTOTAL(109,CapitalSources[TOTALS]) -> 0
B98: STARTUP EXPENSES | D98: TOTALS
B99: Buildings/real estate | D99: =RealEstate[[#Totals],[AMOUNT]] -> 13742.48
B100: Leasehold improvements | D100: =Improvements[[#Totals],[AMOUNT]] -> 60
B101: Capital equipment | D101: =Capital[[#Totals],[AMOUNT]] -> 0
B102: Location/administration expenses | D102: =AdminExpenses[[#Totals],[AMOUNT]] -> 0
B103: Opening inventory | D103: =OpeningInventory[[#Totals],[AMOUNT]] -> 0
B104: Advertising/promotional expenses | D104: =PromoExpenses[[#Totals],[AMOUNT]] -> 0
B105: Other expenses | D105: =OtherExpenses[[#Totals],[AMOUNT]] -> 0
B106: Contingency fund | D106: =SUM('Startup Expenses'!$C$63) -> 0
B107: Working capital | D107: =SUM('Startup Expenses'!$C$65) -> 0
B108: Total | D108: =SUBTOTAL(109,StartupExpenses[TOTALS]) -> 13802.48
B110: SECURITY AND COLLATERAL FOR LOAN PROPOSAL
B111: COLLATERAL FOR LOANS | C111: DESCRIPTION | D111: VALUE
B112: Real estate | D112: 0
B113: Other collateral | D113: 0
B114: Other collateral | D114: 0
B115: Other collateral | D115: 0
B116: Total | D116: =SUBTOTAL(109,Collateral[VALUE]) -> 0
B118: OWNERS
...

Sheet Revenue Estimate
A1: 2L Baby Steps Hydration Pack Cleaning Kit Combo
A2: Sales Channel | B2: Quanity | C2: Price | D2: revenue
A3: E-Commerce | C3: 60 | D3: 60
A4: Vending | B4: 500 | C4: 60
A5: Affiliate | B5: 46 | C5: 40 | D5: 1840

Sheet Event Schedule
A1: Event Funnel
A2: Start Date | B2: End Date | C2: Event | D2: Opportunity (Attendence / Viewers) | E2: Payee | F2: Start Cost | G2: Additional Marketing Budget | H2: Marketing Acticity | I2: Marketing Goal | J2: Service | K2: Est. Minimum Result | L2: Est. Maximum Result | M2: Actual Results
A3: 4/31/19 | C3: FO Pack Launch | E3: InventureX | F3: 5500 | G3: 20000 | H3: Social Posts | J3: Fiber Optic Crowdfunding Campaign Launch
A4: 43589 | B4: 5/519 | C4: Bass Country Grand Rapids | D4: Kyle | E4: D-Town Designz Kyle | N4: 15% Of Sales
A5: 11449 | B5: 43625 | C5: Movement & Spring Awakening Baby Steps GiveAway | E5: MyHydrationPack, D2R, D-Town Designz, | J5: 3 / week give away to promote Features & benefits
A6: 43609 | B6: 43612 | C6: Movement Music Festival | E6: n/a | G6: 500 | J6: Movement Vending @ Detroit Shipping Co.
A7: 43610 | C7: Massive Snails Event
A8: 43623 | C8: Spring Awakening Music Festival | D8: 105000 | E8: D-Town Designz Kyle | G8: 500
C9: Electric Forest Music Festival | D9: 45000
A10: 43609 | C10: Movement
A14: 43376 | B14: slugtopia 3

Sheet Product Cost
A1: Product Cost
A2: Products Funnel | B2: Cost Range | C2: 1000 | D2: 500 | E2: bladder | I2: Import | J2: Cost/Unit | K2: CC Fees | L2: Shipping
A3: LSDREAM | B3: 8660 - 15500 | C3: 5.9 | D3: 7.12 | E3: 3 | I3: 3600 | J3: 8.66-12.5
A4: Adventure Club
A5: Bear Grillz
A6: IMF
A7: WLC
A10: Price / SKU
A11: Products | B11: Cost | C11: Hydration pack | D11: Bladder | E11: Cleaning Kit | F11: Bluetooth Controller | G11: Fiber Optic | H11: Power Bank | I11: MOQ QTY | J11: Import | K11: Price / Unit | N11: CC Fees | O11: Discounts | P11: Bluetooth Controller | Q11: Fiber Optic | R11: Power Bank
A12: Baby Steps Cleaning Bundle | B12: =SUM(C12:E12)*I12+J12 -> 15525 | C12: 6.85 | D12: 3 | E12: 1.79 | F12: 0 | G12: 0 | H12: 0 | I12: 1000 | J12: 3885 | K12: =B12/I12 -> 15.525
A13: MHP Fiber Optic Pack | B13: =SUM(C13:E13)*I13+J13 -> 13735 | C13: 6.85 | D13: 3 | E13: 0 | F13: 0 | G13: 0 | H13: 0 | I13: 1000 | J13: 3885 | K13: =B13/I13 -> 13.735
A14: Baby Steps 2lt HP | C14: 6.85 | D14: 3 | E14: 0 | F14: 0 | G14: 0 | H14: 0
A15: Fiber Optic | C15: 7.28 | D15: 3 | E15: 0 | F15: 2.3 | G15: 5.5 | H15: 5.1
A16: Baby Steps 2lt HP FB | C16: 6.85 | D16: 3 | E16: 0 | F16: 2.3 | G16: 5.5 | H16: 5.1
L17: Brand Royalty | M17: Charity Donation
L18: 0.05 | M18: 0.1
A53: Shithead | C53: 6.85 | D53: 3 | E53: 0 | F53: 2.3 | G53: 5.5 | H53: 5.1

Sheet Sheet1
D4: Products | H4: Products | L4: Products Funnel | Q4: Cost Range | R4: 1000 | S4: 500 | V4: Cost/Unit | W4: CC Fees | X4: Shipping
D5: Shithead | H5: LSDREAM | L5: LSDREAM | M5: 1000 | N5: 5.9 | Q5: 8660 - 15500 | R5: 5.9 | S5: 7.12 | T5: 3 | U5: 3600 | V5: 8.66-12.5
L6: LSDREAM | M6: 500 | N6: 7.12
L7: Adventure Club | M7: 1000
H8: bladder | L8: Bear Grillz | M8: 1000
L9: IMF | M9: 1000
B10: MOQ QTY | D10: Hydration pack | L10: WLC | M10: 1000
B11: 500 | D11: =IFERROR(VLOOKUP($D$5,'Product Cost'!$A$11:$K$150,MATCH(D10,'Product Cost'!$A$11:$K$11,0),0),"") -> 6.85 | L11: Adventure Club | M11: 500
B12: Import Option | D12: Bladder | E12: Qty | F12: Import Price | L12: Bear Grillz | M12: 500
B13: Option B | D13: =IFERROR(VLOOKUP($D$5,'Product Cost'!$A$11:$K$150,MATCH(D12,'Product Cost'!$A$11:$K$11,0),0),"") -> 3 | E13: Option A | F13: 3.89 | L13: IMF | M13: 500
D14: Cleaning Kit | E14: Option B | F14: 4 | H14: Import | L14: WLC | M14: 500
D15: =IFERROR(VLOOKUP($D$5,'Product Cost'!$A$11:$K$150,MATCH(D14,'Product Cost'!$A$11:$K$11,0),0),"") -> 0 | E15: Option C | F15: 6
D16: Bluetooth Controller
D17: =IFERROR(VLOOKUP($D$5,'Product Cost'!$A$11:$K$150,MATCH(D16,'Product Cost'!$A$11:$K$11,0),0),"") -> 2.3
D18: Fiber Optic
D19: =IFERROR(VLOOKUP($D$5,'Product Cost'!$A$11:$K$150,MATCH(D18,'Product Cost'!$A$11:$K$11,0),0),"") -> 5.5
D20: Power Bank
D21: =IFERROR(VLOOKUP($D$5,'Product Cost'!$A$11:$K$150,MATCH(D20,'Product Cost'!$A$11:$K$11,0),0),"") -> 5.1
D22: Import
D23: =IFERROR(VLOOKUP(B13,$E$12:$F$15,2,0),"") -> 4
D24: Price / Unit
D25: =D11+D13+D15+D17+D19+D21+D23 -> 26.75
D27: Cost
D28: =B11*D25 -> 13375

Sheet Sheet2
A1: bag | B1: units | C1: price | D1: revenue | E1: cost | F1: Shipping / pack | G1: Shipping Cost | H1: Royalty % | I1: Royalty $ | J1: Charity % | K1: Charity $ | L1: Profit
A2: Baby Steps | B2: 500 | C2: 65 | D2: 32500 | E2: 7000 | F2: 8 | G2: 4000 | H2: 0.05 | I2: 1075 | J2: 10 | K2: 2042.5 | L2: 18382.5 | M2: 28215/1000
A3: Baby steps | B3: 500 | C3: 45 | D3: 22500 | E3: 7000 | F3: 8 | G3: 4000 | H3: 0.05 | I3: 575 | J3: 10 | K3: 1092.5 | L3: 9832.5
A4: imagine | B4: 1000 | F4: 8 | H4: 0.45 | J4: 10
A5: LSDream | B5: 1000 | C5: 65 | D5: 6500 | F5: 8 | H5: 0.45 | J5: 10
A6: MHP FO APP | B6: 1000 | C6: 110 | D6: 111000 | E6: 30000 | F6: 8 | G6: 8000 | H6: 0 | I6: n/a | J6: 10 | K6: 7200 | L6: 64800
A7: MHP FO CLICk | B7: 1000 | C7: 85 | D7: 85000 | E7: 20000 | F7: 8 | G7: 8000 | H7: 0 | I7: n/a | J7: 10 | K7: 6500 | L7: 58500
C9: Festival | D9: Attendence | E9: 0.005 | F9: Cost | G9: revenue @ 85 | H9: .5% Profit | I9: 0.01 | J9: Cost | K9: Revenue @85 | L9: Profit | M9: Vending | N9: Chariity | O9: Start Date | P9: End Date
C10: Spring Awakening | D10: 105000 | E10: 525 | F10: 21.64 | G10: 44625 | I10: 1500 | M10: 6000 | O10: 43623
A11: 43643 | C11: electric forest | D11: 40000 | E11: 200 | G11: 17000 | I11: 400
A12: 43678 | B12: 43681 | C12: lollapalooza | D12: 400000 | E12: 2000 | I12: 4000
A13: 43700 | C13: mamby | D13: 50000 | E13: 250 | F13: 164500 | G13: 723800 | I13: 500 | M13: 503370
A14: 43707 | B14: 43709 | C14: Ezoo | D14: 98000 | E14: 490 | I14: 980
A15: 43728 | B15: 43730 | C15: Imagine Festival | D15: 35000 | E15: 175 | I15: 350
A16: 43735 | B16: 43737 | C16: Lost Lands | D16: 35000 | E16: 175 | I16: 350
A17: 43741 | C17: Wakaan Festival | D17: 30000 | E17: 150 | I17: 300
A18: 43766 | C18: Freaky Deaky | D18: 60000 | E18: 300 | I18: 600
D20: 453000 | E20: 2265 | F20: 49014.6 | G20: 192525 | H20: 143510 | I20: 11060 | J20: 239338.4 | K20: 940100 | L20: 700761.6

Sheet Sheet3
D4: Festival
D5: Spring Awakening
B6: Products
B7: MHP Fiber Optic Pack | D7: Attendence | G7: 0.005 | H7: Cost | I7: revenue @ 85 | J7: .5% Profit | K7: 0.01 | L7: Cost | M7: Revenue @85 | N7: Profit | O7: Vending | P7: Chariity | Q7: Start Date | R7: End Date
B8: Manufacturing Cost | D8: =IFERROR(VLOOKUP($D$5,Sheet2!$C$9:$O$10,MATCH(Sheet3!D7,Sheet2!$C$9:$P$9,0),0),"") -> 105000
B9: =Sheet1!D25 -> 26.75
B10: Price | D10: .5% Purchase
B11: 60 | D11: =D8*0.005 -> 525
D12: 1% Purchase
D13: =D8*0.01 -> 1050
D14: 3% Purchase
D15: =D8*0.03 -> 3150
D17: .5% Cost
D18: =D11*B9 -> 14043.75
D19: 1% Cost
D20: =D13*B9 -> 28087.5
D21: 3% Cost
D22: =D15*B9 -> 84262.5
D24: Event Cost
D25: 5000
D27: .5% Revenue
D28: =D11*B11 -> 31500
D29: 1% Revenue
D30: =D13*B11 -> 63000
D31: 3% Revenue
D32: =D15*B11 -> 189000
D34: .5% Total Revenue
D35: =D28-D18-D25 -> 12456.25
D36: 1% Total Revenue
D37: =D30-D20-D25 -> 29912.5
D38: 3% Total Revenue
D39: =D32-D22-D25 -> 99737.5
D41: .5% Artist Royalty
D42: =D35*0.005 -> 62.28125
D43: 1% Artist Royalty
D44: =D37*0.01 -> 299.125
D45: 3% Artist Royalty
D46: =D39*0.03 -> 2992.125
D48: .5% Charity Donation
D49: =(D35-D42)*0.1 -> 1239.3969
D50: 1% Charity Donation
D51: =(D37-D44)*0.1 -> 2961.3375
D52: 3% Charity Donation
D53: =(D39-D46)*0.1 -> 9674.5375
D55: .5% Final Profit
D56: =D35-D42-D49 -> 11154.572
D57: 1% Final Profit
D58: =D37-D44-D51 -> 26652.037
D59: 3% Final Profit
D60: =D39-D46-D53 -> 87070.837

Sheet Product Sales Cost
A1: Event Costs / Opportunity [ # of Attendees] | K1: E-Commerce Sales
B2: Inventory | C2: Protoype | D2: Manufacture | E2: Payment Processing | F2: Channel / Merchant Fee | G2: Vending | H2: Product Giveaway | K2: Channel | L2: MSRP | M2: Price | N2: Discount | O2: Channel Fee | P2: Payment Processing | Q2: Shipping | R2: Partner Royalty | S2: Charity Donation | T2: Profit
A3: BabySteps 2L Cleaning Kit Bundle | B3: 1000 | C3: 575 | D3: 15525 | K3: Website
A4: Concert | K4: Amazon
A5: Charity | K5: Google
A6: Fair | K6: FB MarketPlace
A7: Race | K7: paypal | L7: 85 | M7: 60 | O7: 0.03 | P7: 0.3 | R7: Point to Partner Table | S7: point to partner table

Sheet Partnerships
A1: P
A2: name | B2: type | C2: Percentage | D2: Product
A3: Chomped Creations | B3: Brand | C3: 0.05 | D3: Baby Steps
A4: DanceSafe | B4: Charity | C4: 0.1

Sheet Sales data
A2: Channel | B2: Qty | C2: Payment Method | D2: Site Fee | E2: Shipping | F2: Discount
A3: MyHydrationPack.com | D3: 48.99
A4: Amazon
A5: Google
A6: Facebook

Sheet Marketing Schedule
A1: Marketing Plan
A2: Start Date | B2: End Date | C2: Event | D2: Team | E2: Marketing Activity | F2: Est. Marketing Cost | G2: Marketing Goal | H2: KPI | I2: Est. Results | J2: Actual Results
A3: 11449 | B3: 43625 | C3: Movement & Spring Awakening Baby Steps GiveAway | D3: MyHydrationPack | E3: Giveaway | F3: packs cost + shipping | G3: Brand Recognition, Features & Benefits, UGC | H3: Post Shares, Page Likes, Post Interaction with UGC
A4: 43609 | B4: 43612 | C4: Movement Music Festival | D4: MyHydrationPack | E4: Bracelet Giveaway @ Festival | F4: Festival Ticket + wristband + Food + Pack | G4: FO Mailing List Signups, Baby Steps Sales, UGC
A5: 43609 | B5: 43612 | C5: Movement Music Festival | D5: DanceSafe | E5: Giveaway | G5: Promote Brand, Partnership Importance of Hydration | H5: Movement Vending Baby Steps Sales
A6: 43610 | C6: Massive Snails Event | D6: MHP, D-Town Designz Kyle
A7: 43623 | C7: Spring Awakening Music Festival | D7: D-Town Designz Kyle, D2R
C8: Electric Forest Music Festival

Sheet Influencer
A1: Influencer
A2: Who | B2: Type | C2: Following | D2: Goal | E2: Result
A3: LSDream | B3: Artist
A4: Bear Grillz | B4: Artist
A5: Protohype | B5: Artist
A6: Snails | B6: Artist
A7: Dion Timmer | B7: Artist
A8: Excision | B8: Artist
A9: Kendall (DT G/F) | B9: Dion Timmer GF
A10: Emily | B10: Excision GF
A11: Dancesafe | B11: 501c3
A12: Fresh Music Freaks | B12: Blog
A13: Greg Lillie

Sheet Sales Funnel
A1: Sales Funnel
A2: Business | B2: QTY | C2: cost | D2: Sale Price | E2: Import Cost | F2: Revenue | G2: Funnel Stage | H2: Days In Stage | I2: stage Start Date
A3: DanceSafe WLC | B3: 500 | G3: PA
A4: LSDream | B4: 500 | G4: Phiysical | I4: 43550
A5: Snails | B5: 500
A6: Bear Grillz | B6: 500
A7: IMF | B7: 1000

Sheet MFG & Import Costs
A1: Product Costs
A2: Item | B2: Description | C2: Qty | D2: FOB(Xiamen) | E2: Amount
D3: Unit price
A5: Hydration pack | B5: Baby step hydration pack | C5: 1000 | D5: 6.85 | E5: 6850
A6: Water bladder | B6: PEVA water bladder | C6: 1000 | D6: 3 | E6: 3000
A7: Cleaning kit set | B7: 4 pcs per set cleaning kit | C7: 1000 | D7: 1.79 | E7: 1790
A8: Water bladder | B8: PEVA water bladder | C8: 50 | D8: 3 | E8: 150
A9: Cleaning kit set | B9: 4pcs per set cleaning kit | C9: 20 | D9: 1.79 | E9: 35.8
A11: Discount : 3% | B11: Total : $11,290.80
A12: Express Shipping for 40 | E12: 285
A13: Air Shipping to door | E13: 3600
A14: Prototype | D14: 250
A15: Deposit | D15: 3387
